odoo/addons/account_bank_statement_import_camt_oca/README.rst
odoo/addons/account_bank_statement_import_camt_oca/__init__.py
odoo/addons/account_bank_statement_import_camt_oca/__manifest__.py
odoo/addons/account_bank_statement_import_camt_oca/i18n/account_bank_statement_import_camt_oca.pot
odoo/addons/account_bank_statement_import_camt_oca/i18n/de.po
odoo/addons/account_bank_statement_import_camt_oca/i18n/es.po
odoo/addons/account_bank_statement_import_camt_oca/i18n/fa.po
odoo/addons/account_bank_statement_import_camt_oca/i18n/fi.po
odoo/addons/account_bank_statement_import_camt_oca/i18n/fr.po
odoo/addons/account_bank_statement_import_camt_oca/i18n/fr_CH.po
odoo/addons/account_bank_statement_import_camt_oca/i18n/gl.po
odoo/addons/account_bank_statement_import_camt_oca/i18n/hr.po
odoo/addons/account_bank_statement_import_camt_oca/i18n/lt_LT.po
odoo/addons/account_bank_statement_import_camt_oca/i18n/nb_NO.po
odoo/addons/account_bank_statement_import_camt_oca/i18n/nl.po
odoo/addons/account_bank_statement_import_camt_oca/i18n/pt_BR.po
odoo/addons/account_bank_statement_import_camt_oca/i18n/pt_PT.po
odoo/addons/account_bank_statement_import_camt_oca/i18n/sl.po
odoo/addons/account_bank_statement_import_camt_oca/models/__init__.py
odoo/addons/account_bank_statement_import_camt_oca/models/account_bank_statement_import.py
odoo/addons/account_bank_statement_import_camt_oca/models/account_bank_statement_line.py
odoo/addons/account_bank_statement_import_camt_oca/models/account_journal.py
odoo/addons/account_bank_statement_import_camt_oca/models/bank_statement.py
odoo/addons/account_bank_statement_import_camt_oca/models/parser.py
odoo/addons/account_bank_statement_import_camt_oca/readme/CONTRIBUTORS.rst
odoo/addons/account_bank_statement_import_camt_oca/readme/DESCRIPTION.rst
odoo/addons/account_bank_statement_import_camt_oca/static/description/icon.png
odoo/addons/account_bank_statement_import_camt_oca/static/description/index.html
odoo13_addon_account_bank_statement_import_camt_oca-13.0.1.1.2.dist-info/METADATA
odoo13_addon_account_bank_statement_import_camt_oca-13.0.1.1.2.dist-info/WHEEL
odoo13_addon_account_bank_statement_import_camt_oca-13.0.1.1.2.dist-info/top_level.txt
odoo13_addon_account_bank_statement_import_camt_oca-13.0.1.1.2.dist-info/RECORD
